dash_player/DashPlayer.py
dash_player/__init__.py
dash_player/_imports_.py
dash_player/async-dashplayer.js
dash_player/async-dashplayer.js.map
dash_player/dash_player.min.js
dash_player/dash_player.min.js.map
dash_player/metadata.json
dash_player/package.json
dash_player-1.1.0.dist-info/LICENSE
dash_player-1.1.0.dist-info/METADATA
dash_player-1.1.0.dist-info/WHEEL
dash_player-1.1.0.dist-info/top_level.txt
dash_player-1.1.0.dist-info/RECORD
