Metadata-Version: 2.1
Name: dash_player
Version: 1.1.0
Summary: A Dash component for playing a variety of URLs.
Home-page: https://github.com/plotly/dash-player
Author: Xing Han Lu <xinghan@plot.ly>
License: MIT
Classifier: Programming Language :: Python :: 3
Classifier: Framework :: Dash
Classifier: License :: OSI Approved :: MIT License
Classifier: Operating System :: OS Independent
Requires-Python: >=3.6
License-File: LICENSE
